terraform.py
terraform_bin-1.0.1.data/data/lib/terraform_darwin
terraform_bin-1.0.1.data/data/lib/terraform_linux
terraform_bin-1.0.1.data/data/lib/terraform_windows.exe
terraform_bin-1.0.1.dist-info/LICENSE
terraform_bin-1.0.1.dist-info/METADATA
terraform_bin-1.0.1.dist-info/WHEEL
terraform_bin-1.0.1.dist-info/entry_points.txt
terraform_bin-1.0.1.dist-info/top_level.txt
terraform_bin-1.0.1.dist-info/RECORD
