Metadata-Version: 2.1
Name: terraform-bin
Version: 1.0.1
Summary: UNKNOWN
Home-page: https://github.com/epiphany-platform/terraform-bin
Author: Epiphany Team
Author-email: 
License: Apache License Version 2.0
Platform: UNKNOWN
